gamuth/__init__.py
gamuth/gamuth.py
gamuth/test.py
gamuth/testlib.py
gamuth-0.0.1.dist-info/METADATA
gamuth-0.0.1.dist-info/WHEEL
gamuth-0.0.1.dist-info/entry_points.txt
gamuth-0.0.1.dist-info/top_level.txt
gamuth-0.0.1.dist-info/RECORD
