Metadata-Version: 2.1
Name: gamuth
Version: 0.0.1
Summary: Guide to Advanced Music Theory
Home-page: https://github.com/fabianmoss/gamuth
Author: Fabian C. Moss
Author-email: fabianmoss@gmail.com
License: MIT
Platform: UNKNOWN
Classifier: License :: OSI Approved :: MIT License
Classifier: Programming Language :: Python :: 3
Classifier: Programming Language :: Python :: 3.7
Requires-Dist: numpy
